graphql_auth/__init__.py
graphql_auth/apps.py
graphql_auth/backends.py
graphql_auth/bases.py
graphql_auth/constants.py
graphql_auth/decorators.py
graphql_auth/exceptions.py
graphql_auth/forms.py
graphql_auth/mixins.py
graphql_auth/models.py
graphql_auth/mutations.py
graphql_auth/relay.py
graphql_auth/schema.py
graphql_auth/settings.py
graphql_auth/shortcuts.py
graphql_auth/signals.py
graphql_auth/types.py
graphql_auth/utils.py
graphql_auth/migrations/0001_initial.py
graphql_auth/migrations/__init__.py
graphql_auth/templates/email/activation_email.html
graphql_auth/templates/email/activation_subject.txt
graphql_auth/templates/email/password_reset_email.html
graphql_auth/templates/email/password_reset_subject.txt
graphql_auth/templates/email/password_set_email.html
graphql_auth/templates/email/password_set_subject.txt
testproject/__init__.py
testproject/manage.py
testproject/pseudo_async_email_support.py
testproject/schema.py
testproject/settings.py
testproject/urls.py
django_graphql_auth-0.3.16.dist-info/LICENSE
django_graphql_auth-0.3.16.dist-info/METADATA
django_graphql_auth-0.3.16.dist-info/WHEEL
django_graphql_auth-0.3.16.dist-info/top_level.txt
django_graphql_auth-0.3.16.dist-info/RECORD
