Metadata-Version: 2.1
Name: django-graphql-auth
Version: 0.3.16
Summary: Graphql and relay authentication with Graphene for Django.
Home-page: https://github.com/PedroBern/django-graphql-auth
Author: pedrobern
Author-email: pedrobermoreira@gmail.com
Maintainer: pedrobern
License: MIT
Project-URL: Documentation, https://django-graphql-auth.readthedocs.io/en/latest/
Project-URL: Issues, https://github.com/PedroBern/django-graphql-auth/issues
Keywords: api graphql rest relay graphene auth
Platform: UNKNOWN
Classifier: Development Status :: 4 - Beta
Classifier: Environment :: Web Environment
Classifier: Intended Audience :: Developers
Classifier: License :: OSI Approved :: MIT License
Classifier: Operating System :: OS Independent
Classifier: Programming Language :: Python
Classifier: Programming Language :: Python :: 3.6
Classifier: Programming Language :: Python :: 3.7
Classifier: Programming Language :: Python :: 3.8
Classifier: Framework :: Django
Classifier: Framework :: Django :: 2.1
Classifier: Framework :: Django :: 2.2
Classifier: Framework :: Django :: 3.0
Provides-Extra: test
Provides-Extra: dev
